invenio_collections/__init__.py
invenio_collections/api.py
invenio_collections/config.py
invenio_collections/errors.py
invenio_collections/ext.py
invenio_collections/models.py
invenio_collections/proxies.py
invenio_collections/searchapp.py
invenio_collections/tasks.py
invenio_collections/views.py
invenio_collections/alembic/1748509182_create_collections_branch.py
invenio_collections/alembic/425b691f768b_create_collections_tables.py
invenio_collections/resources/__init__.py
invenio_collections/resources/config.py
invenio_collections/resources/resource.py
invenio_collections/services/__init__.py
invenio_collections/services/config.py
invenio_collections/services/links.py
invenio_collections/services/results.py
invenio_collections/services/schema.py
invenio_collections/services/service.py
invenio_collections-3.0.1.dist-info/METADATA
invenio_collections-3.0.1.dist-info/WHEEL
invenio_collections-3.0.1.dist-info/entry_points.txt
invenio_collections-3.0.1.dist-info/licenses/AUTHORS.rst
invenio_collections-3.0.1.dist-info/licenses/LICENSE
invenio_collections-3.0.1.dist-info/RECORD
