Metadata-Version: 2.4
Name: invenio-collections
Version: 3.0.1
Summary: Invenio module for organizing metadata into collections.
Project-URL: Repository, https://github.com/inveniosoftware/invenio-collections
Author-email: CERN <info@inveniosoftware.org>
License: MIT License
License-File: AUTHORS.rst
License-File: LICENSE
Keywords: collections,invenio,inveniordm,rdm
Classifier: Environment :: Web Environment
Classifier: Intended Audience :: Developers
Classifier: License :: OSI Approved :: MIT License
Classifier: Operating System :: OS Independent
Classifier: Programming Language :: Python
Classifier: Programming Language :: Python :: 3
Classifier: Programming Language :: Python :: 3.9
Classifier: Programming Language :: Python :: 3.10
Classifier: Programming Language :: Python :: 3.11
Classifier: Programming Language :: Python :: 3.12
Classifier: Programming Language :: Python :: 3.13
Classifier: Topic :: Internet :: WWW/HTTP :: Dynamic Content
Classifier: Topic :: Software Development :: Libraries :: Python Modules
Requires-Python: >=3.9
Requires-Dist: invenio-administration<5.0.0,>=4.0.0
Requires-Dist: invenio-communities<23.0.0,>=22.0.0
Requires-Dist: invenio-rdm-records<24.0.0,>=23.0.0
Requires-Dist: invenio-records-resources<9.0.0,>=8.0.0
Requires-Dist: invenio-search-ui<5.0.0,>=4.0.0
Provides-Extra: opensearch2
Requires-Dist: invenio-search[opensearch2]<4.0.0,>=3.0.0; extra == 'opensearch2'
Provides-Extra: tests
Requires-Dist: invenio-app<3.0.0,>=2.0.0; extra == 'tests'
Requires-Dist: invenio-db[mysql,postgresql]<3.0.0,>=2.0.0; extra == 'tests'
Requires-Dist: pytest-black>=0.3.0; extra == 'tests'
Requires-Dist: pytest-invenio<4.0.0,>=3.0.0; extra == 'tests'
Requires-Dist: sphinx>=4.5; extra == 'tests'
